README.md
setup.cfg
setup.py
module_hot_reload/__init__.py
module_hot_reload/module_wrappers.py
module_hot_reload/reloaders.py
module_hot_reload/utils.py
module_hot_reload/watchdog_handlers.py
module_hot_reload.egg-info/PKG-INFO
module_hot_reload.egg-info/SOURCES.txt
module_hot_reload.egg-info/dependency_links.txt
module_hot_reload.egg-info/requires.txt
module_hot_reload.egg-info/top_level.txt