Metadata-Version: 2.1
Name: module-hot-reload
Version: 0.0.8
Summary: Package for reloading other packages and modules while Python is running
Home-page: https://github.com/Borisoid/module_hot_reload
Author: borisoid
License: MIT
Keywords: module,hot,reload,runtime,watch
Platform: UNKNOWN
Classifier: Development Status :: 3 - Alpha
Classifier: Intended Audience :: Developers
Classifier: Topic :: Software Development :: Libraries :: Python Modules
Classifier: License :: OSI Approved :: MIT License
Classifier: Programming Language :: Python :: 3
Classifier: Programming Language :: Python :: 3.8
Classifier: Operating System :: Microsoft :: Windows
Classifier: Operating System :: POSIX :: Linux
